woohoo_pdns/__init__.py
woohoo_pdns/__main__.py
woohoo_pdns/load.py
woohoo_pdns/meta.py
woohoo_pdns/pdns.py
woohoo_pdns/util.py
woohoo_pdns/api/__init__.py
woohoo_pdns/api/api.py
woohoo_pdns/api/config.py
woohoo_pdns/api/db.py
woohoo_pdns/tests/__init__.py
woohoo_pdns/tests/test_basic.py
woohoo_pdns-2019.1.3.dist-info/LICENSE
woohoo_pdns-2019.1.3.dist-info/METADATA
woohoo_pdns-2019.1.3.dist-info/WHEEL
woohoo_pdns-2019.1.3.dist-info/entry_points.txt
woohoo_pdns-2019.1.3.dist-info/top_level.txt
woohoo_pdns-2019.1.3.dist-info/RECORD
