Metadata-Version: 2.1
Name: woohoo-pdns
Version: 2019.1.3
Summary: woohoo pDNS implementation
Home-page: https://gitlab.com/scherand/woohoo-pdns
Author: Andreas Scherrer
Author-email: andreas@scherrer.io
License: MIT License
Project-URL: Bug Tracker, https://gitlab.com/scherand/woohoo-pdns/issues
Project-URL: Documentation, https://woohoo-pdns.readthedocs.io
Project-URL: Source Code, https://gitlab.com/scherand/woohoo-pdns
Platform: UNKNOWN
Classifier: Programming Language :: Python :: 3
Classifier: Programming Language :: Python :: 3.6
Requires-Dist: alembic
Requires-Dist: flask
Requires-Dist: flask-httpauth
Requires-Dist: gunicorn
Requires-Dist: psycopg2-binary
Requires-Dist: python-dateutil
Requires-Dist: pyyaml
Requires-Dist: requests
Requires-Dist: sphinx
Requires-Dist: sqlalchemy
